smart_pandas/__init__.py
smart_pandas-0.0.16.dist-info/METADATA
smart_pandas-0.0.16.dist-info/WHEEL
smart_pandas-0.0.16.dist-info/RECORD
