Metadata-Version: 2.1
Name: smart-pandas
Version: 0.0.16
Summary: Supercharge your data science workflows with Ollama models
Author: Muntakimur Rahaman
Author-email: muntakim.cse@gmail.com
Requires-Python: >=3.10.12,<4.0.0
Classifier: Programming Language :: Python :: 3
Classifier: Programming Language :: Python :: 3.11
Classifier: Programming Language :: Python :: 3.12
Requires-Dist: matplotlib
Requires-Dist: numpy
Requires-Dist: ollama
Requires-Dist: pandas
Requires-Dist: scikit-learn
Requires-Dist: seaborn
